{
  "cost_estimates": [
    {
      "ride_type": "lyft_plus",
      "estimated_duration_seconds": 1006,
      "estimated_distance_miles": 2.87,
      "estimated_cost_cents_max": 3100,
      "primetime_percentage": "25%",
      "currency": "USD",
      "estimated_cost_cents_min": 2100,
      "display_name": "Lyft Plus",
      "primetime_confirmation_token": null
    },
    {
      "ride_type": "lyft_line",
      "estimated_duration_seconds": 1006,
      "estimated_distance_miles": 2.87,
      "estimated_cost_cents_max": 1099,
      "primetime_percentage": "0%",
      "currency": "USD",
      "estimated_cost_cents_min": 1099,
      "display_name": "Lyft Line",
      "primetime_confirmation_token": null
    },
    {
      "ride_type": "lyft",
      "estimated_duration_seconds": 1006,
      "estimated_distance_miles": 2.87,
      "estimated_cost_cents_max": 2100,
      "primetime_percentage": "25%",
      "currency": "USD",
      "estimated_cost_cents_min": 1300,
      "display_name": "Lyft",
      "primetime_confirmation_token": null
    }
  ]
}
